minigen/__init__.py
minigen/agent.py
minigen/context.py
minigen/network.py
minigen/state.py
minigen/tool.py
minigen/primitives/__init__.py
minigen/primitives/chain.py
minigen/primitives/parallel.py
minigen/primitives/router.py
minigen/utils/logging.py
minigen-0.1.0.dist-info/licenses/LICENSE
minigen-0.1.0.dist-info/METADATA
minigen-0.1.0.dist-info/WHEEL
minigen-0.1.0.dist-info/top_level.txt
minigen-0.1.0.dist-info/RECORD
