Metadata-Version: 2.4
Name: minigen
Version: 0.1.0
Summary: a lightweight python framework library for building agents
Requires-Python: >=3.13
License-File: LICENSE
Requires-Dist: build>=1.3.0
Requires-Dist: openai>=1.98.0
Requires-Dist: requests>=2.32.4
Requires-Dist: tinyio>=0.1.4
Requires-Dist: twine>=6.1.0
Dynamic: license-file
